setup.cfg
setup.py
nose2_cprofiler/__init__.py
nose2_cprofiler/plugins/__init__.py
nose2_cprofiler/plugins/cprof.py
nose2_cprofiler_plugin.egg-info/PKG-INFO
nose2_cprofiler_plugin.egg-info/SOURCES.txt
nose2_cprofiler_plugin.egg-info/dependency_links.txt
nose2_cprofiler_plugin.egg-info/top_level.txt