Metadata-Version: 1.0
Name: nose2-cprofiler-plugin
Version: 1.0.2
Summary: cprofiler plugin for nose2
Home-page: https://github.com/stratoscale/nose2-cprofiler-plugin
Author: Noam Chadash
Author-email: noam@stratoscale.com
License: UNKNOWN
Keywords: cprofiler nose2 plugin
Platform: UNKNOWN
